{
   "closing_ranks_2021": {
      "CSE": {
         "OC BOYS": 9751,
         "OC GIRLS": 10082,
         "BC_A BOYS": 23393,
         "BC_A GIRLS": 23393,
         "BC_B BOYS": 14028,
         "BC_B GIRLS": 15879,
         "BC_C BOYS": 38300,
         "BC_C GIRLS": 50487,
         "BC_D BOYS": 14266,
         "BC_D GIRLS": 15250,
         "BC_E BOYS": 23064,
         "BC_E GIRLS": 35930,
         "SC BOYS": 34741,
         "SC GIRLS": 38122,
         "ST BOYS": 25197,
         "ST GIRLS": 39420
      },
      "CSM": {
         "OC BOYS": 11263,
         "OC GIRLS": 11788,
         "BC_A BOYS": 27648,
         "BC_A GIRLS": 32095,
         "BC_B BOYS": 15822,
         "BC_B GIRLS": 16502,
         "BC_C BOYS": 11263,
         "BC_C GIRLS": 11788,
         "BC_D BOYS": 14947,
         "BC_D GIRLS": 17902,
         "BC_E BOYS": 38501,
         "BC_E GIRLS": 43414,
         "SC BOYS": 41409,
         "SC GIRLS": 65520,
         "ST BOYS": 38982,
         "ST GIRLS": 38982
      },
      "INF": {
         "OC BOYS": 12889,
         "OC GIRLS": 14215,
         "BC_A BOYS": 28384,
         "BC_A GIRLS": 47962,
         "BC_B BOYS": 18526,
         "BC_B GIRLS": 18526,
         "BC_C BOYS": 12889,
         "BC_C GIRLS": 14215,
         "BC_D BOYS": 15084,
         "BC_D GIRLS": 18489,
         "BC_E BOYS": 31662,
         "BC_E GIRLS": 31662,
         "SC BOYS": 49696,
         "SC GIRLS": 53187,
         "ST BOYS": 47405,
         "ST GIRLS": 47405
      },
      "CSC": {
         "OC BOYS": 13381,
         "OC GIRLS": 14227,
         "BC_A BOYS": 32205,
         "BC_A GIRLS": 38855,
         "BC_B BOYS": 18597,
         "BC_B GIRLS": 20689,
         "BC_C BOYS": 14719,
         "BC_C GIRLS": 14719,
         "BC_D BOYS": 17800,
         "BC_D GIRLS": 19770,
         "BC_E BOYS": 41103,
         "BC_E GIRLS": 94159,
         "SC BOYS": 52406,
         "SC GIRLS": 69503,
         "ST BOYS": 45689,
         "ST GIRLS": 62329
      },
      "ECE": {
         "OC BOYS": 23100,
         "OC GIRLS": 23917,
         "BC_A BOYS": 57077,
         "BC_A GIRLS": 61932,
         "BC_B BOYS": 31453,
         "BC_B GIRLS": 32286,
         "BC_C BOYS": 23100,
         "BC_C GIRLS": 33980,
         "BC_D BOYS": 29348,
         "BC_D GIRLS": 38720,
         "BC_E BOYS": 54128,
         "BC_E GIRLS": 65629,
         "SC BOYS": 80554,
         "SC GIRLS": 106853,
         "ST BOYS": 62043,
         "ST GIRLS": 62043
      },
      "EEE": {
         "OC BOYS": 31711,
         "OC GIRLS": 59601,
         "BC_A BOYS": 83724,
         "BC_A GIRLS": 92421,
         "BC_B BOYS": 66862,
         "BC_B GIRLS": 66862,
         "BC_C BOYS": 51735,
         "BC_C GIRLS": 59601,
         "BC_D BOYS": 50759,
         "BC_D GIRLS": 59601,
         "BC_E BOYS": 106789,
         "BC_E GIRLS": 106789,
         "SC BOYS": 64032,
         "SC GIRLS": 120365,
         "ST BOYS": 70257,
         "ST GIRLS": 107384
      },
      "CIV": {
         "OC BOYS": 51254,
         "OC GIRLS": 57344,
         "BC_A BOYS": 72277,
         "BC_A GIRLS": 72277,
         "BC_B BOYS": 74477,
         "BC_B GIRLS": 87645,
         "BC_C BOYS": 51254,
         "BC_C GIRLS": 57344,
         "BC_D BOYS": 66274,
         "BC_D GIRLS": 77762,
         "BC_E BOYS": 51254,
         "BC_E GIRLS": 57344,
         "SC BOYS": 118368,
         "SC GIRLS": 118368,
         "ST BOYS": 68081,
         "ST GIRLS": 117652
      },
      "MEC": {
         "OC BOYS": 52066,
         "OC GIRLS": 76644,
         "BC_A BOYS": 106520,
         "BC_A GIRLS": 106520,
         "BC_B BOYS": 65586,
         "BC_B GIRLS": 83912,
         "BC_C BOYS": 52066,
         "BC_C GIRLS": 76644,
         "BC_D BOYS": 93208,
         "BC_D GIRLS": 94540,
         "BC_E BOYS": 81139,
         "BC_E GIRLS": 90816,
         "SC BOYS": 118891,
         "SC GIRLS": 118891,
         "ST BOYS": 75264,
         "ST GIRLS": 120811
      }
   },
   "closing_ranks_2020": {
      "CSE": {
         "OC BOYS": 8692,
         "OC GIRLS": 8692,
         "BC_A BOYS": 32235,
         "BC_A GIRLS": 44206,
         "BC_B BOYS": 14025,
         "BC_B GIRLS": 15926,
         "BC_C BOYS": 24651,
         "BC_C GIRLS": 55423,
         "BC_D BOYS": 14430,
         "BC_D GIRLS": 14849,
         "BC_E BOYS": 20595,
         "BC_E GIRLS": 28178,
         "SC BOYS": 43384,
         "SC GIRLS": 45743,
         "ST BOYS": 30778,
         "ST GIRLS": 47543
      },
      "INF": {
         "OC BOYS": 11035,
         "OC GIRLS": 11035,
         "BC_A BOYS": 36990,
         "BC_A GIRLS": 39435,
         "BC_B BOYS": 18430,
         "BC_B GIRLS": 18430,
         "BC_C BOYS": 11035,
         "BC_C GIRLS": 11035,
         "BC_D BOYS": 16606,
         "BC_D GIRLS": 16606,
         "BC_E BOYS": 28537,
         "BC_E GIRLS": 28537,
         "SC BOYS": 63249,
         "SC GIRLS": 68256,
         "ST BOYS": 34070,
         "ST GIRLS": 61901
      },
      "CSM": {
         "OC BOYS": 10346,
         "OC GIRLS": 10346,
         "BC_A BOYS": 33022,
         "BC_A GIRLS": 41196,
         "BC_B BOYS": 15894,
         "BC_B GIRLS": 17529,
         "BC_C BOYS": 10346,
         "BC_C GIRLS": 36835,
         "BC_D BOYS": 17447,
         "BC_D GIRLS": 17447,
         "BC_E BOYS": 37753,
         "BC_E GIRLS": 61016,
         "SC BOYS": 73288,
         "SC GIRLS": 73576,
         "ST BOYS": 79688,
         "ST GIRLS": 80042
      },
      "CSC": {
         "OC BOYS": 12362,
         "OC GIRLS": 13475,
         "BC_A BOYS": 47203,
         "BC_A GIRLS": 48342,
         "BC_B BOYS": 19001,
         "BC_B GIRLS": 20172,
         "BC_C BOYS": 77384,
         "BC_C GIRLS": 77384,
         "BC_D BOYS": 19819,
         "BC_D GIRLS": 23938,
         "BC_E BOYS": 46263,
         "BC_E GIRLS": 46263,
         "SC BOYS": 82842,
         "SC GIRLS": 82842,
         "ST BOYS": 69563,
         "ST GIRLS": 69596
      },
      "MEC": {
         "OC BOYS": 19070,
         "OC GIRLS": 59003,
         "BC_A BOYS": 76047,
         "BC_A GIRLS": 76047,
         "BC_B BOYS": 79201,
         "BC_B GIRLS": 81235,
         "BC_C BOYS": 19070,
         "BC_C GIRLS": 59003,
         "BC_D BOYS": 52324,
         "BC_D GIRLS": 75241,
         "BC_E BOYS": 52827,
         "BC_E GIRLS": 59003,
         "SC BOYS": 78737,
         "SC GIRLS": 78873,
         "ST BOYS": 49015,
         "ST GIRLS": 84812
      },
      "ECE": {
         "OC BOYS": 15044,
         "OC GIRLS": 15044,
         "BC_A BOYS": 47270,
         "BC_A GIRLS": 62811,
         "BC_B BOYS": 23721,
         "BC_B GIRLS": 23912,
         "BC_C BOYS": 75229,
         "BC_C GIRLS": 75229,
         "BC_D BOYS": 23969,
         "BC_D GIRLS": 25332,
         "BC_E BOYS": 59318,
         "BC_E GIRLS": 59318,
         "SC BOYS": 67989,
         "SC GIRLS": 72446,
         "ST BOYS": 42935,
         "ST GIRLS": 66783
      },
      "EEE": {
         "OC BOYS": 20787,
         "OC GIRLS": 24778,
         "BC_A BOYS": 20787,
         "BC_A GIRLS": 24778,
         "BC_B BOYS": 45112,
         "BC_B GIRLS": 75909,
         "BC_C BOYS": 20787,
         "BC_C GIRLS": 24778,
         "BC_D BOYS": 30615,
         "BC_D GIRLS": 67227,
         "BC_E BOYS": 68152,
         "BC_E GIRLS": 68152,
         "SC BOYS": 69905,
         "SC GIRLS": 73572,
         "ST BOYS": 34692,
         "ST GIRLS": 50932
      },
      "CIV": {
         "OC BOYS": 33134,
         "OC GIRLS": 40388,
         "BC_A BOYS": 75995,
         "BC_A GIRLS": 75995,
         "BC_B BOYS": 63798,
         "BC_B GIRLS": 63798,
         "BC_C BOYS": 33134,
         "BC_C GIRLS": 40388,
         "BC_D BOYS": 46577,
         "BC_D GIRLS": 67480,
         "BC_E BOYS": 76114,
         "BC_E GIRLS": 80932,
         "SC BOYS": 73310,
         "SC GIRLS": 74770,
         "ST BOYS": 44828,
         "ST GIRLS": 44828
      }
   },
   "closing_ranks_2019": {
      "CSE": {
         "OC BOYS": 9922,
         "OC GIRLS": 9922,
         "BC_A BOYS": 32924,
         "BC_A GIRLS": 32924,
         "BC_B BOYS": 16251,
         "BC_B GIRLS": 16251,
         "BC_C BOYS": 56161,
         "BC_C GIRLS": 56161,
         "BC_D BOYS": 15835,
         "BC_D GIRLS": 16783,
         "BC_E BOYS": 34621,
         "BC_E GIRLS": 60772,
         "SC BOYS": 58274,
         "SC GIRLS": 58274,
         "ST BOYS": 34176,
         "ST GIRLS": 45143
      },
      "INF": {
         "OC BOYS": 12755,
         "OC GIRLS": 12755,
         "BC_A BOYS": 51800,
         "BC_A GIRLS": 59937,
         "BC_B BOYS": 19514,
         "BC_B GIRLS": 19514,
         "BC_C BOYS": 12755,
         "BC_C GIRLS": 12755,
         "BC_D BOYS": 20028,
         "BC_D GIRLS": 20028,
         "BC_E BOYS": 40234,
         "BC_E GIRLS": 43265,
         "SC BOYS": 77287,
         "SC GIRLS": 83148,
         "ST BOYS": 56810,
         "ST GIRLS": 56810
      },
      "ECE": {
         "OC BOYS": 14188,
         "OC GIRLS": 14232,
         "BC_A BOYS": 46263,
         "BC_A GIRLS": 57803,
         "BC_B BOYS": 22515,
         "BC_B GIRLS": 22515,
         "BC_C BOYS": 82746,
         "BC_C GIRLS": 86916,
         "BC_D BOYS": 22466,
         "BC_D GIRLS": 24542,
         "BC_E BOYS": 55694,
         "BC_E GIRLS": 55694,
         "SC BOYS": 73610,
         "SC GIRLS": 82796,
         "ST BOYS": 54762,
         "ST GIRLS": 67262
      },
      "CIV": {
         "OC BOYS": 28049,
         "OC GIRLS": 29230,
         "BC_A BOYS": 48527,
         "BC_A GIRLS": 57810,
         "BC_B BOYS": 43733,
         "BC_B GIRLS": 54724,
         "BC_C BOYS": 28049,
         "BC_C GIRLS": 60890,
         "BC_D BOYS": 38264,
         "BC_D GIRLS": 47235,
         "BC_E BOYS": 82446,
         "BC_E GIRLS": 82446,
         "SC BOYS": 72220,
         "SC GIRLS": 73411,
         "ST BOYS": 47771,
         "ST GIRLS": 75446
      },
      "MEC": {
         "OC BOYS": 24871,
         "OC GIRLS": 50121,
         "BC_A BOYS": 77418,
         "BC_A GIRLS": 81834,
         "BC_B BOYS": 49450,
         "BC_B GIRLS": 77897,
         "BC_C BOYS": 24871,
         "BC_C GIRLS": 50121,
         "BC_D BOYS": 45954,
         "BC_D GIRLS": 50121,
         "BC_E BOYS": 87823,
         "BC_E GIRLS": 87823,
         "SC BOYS": 87718,
         "SC GIRLS": 87718,
         "ST BOYS": 59020,
         "ST GIRLS": 87686
      },
      "EEE": {
         "OC BOYS": 18177,
         "OC GIRLS": 22482,
         "BC_A BOYS": 84062,
         "BC_A GIRLS": 84062,
         "BC_B BOYS": 35990,
         "BC_B GIRLS": 39862,
         "BC_C BOYS": 42347,
         "BC_C GIRLS": 42347,
         "BC_D BOYS": 42416,
         "BC_D GIRLS": 42416,
         "BC_E BOYS": 88644,
         "BC_E GIRLS": 88644,
         "SC BOYS": 75955,
         "SC GIRLS": 84739,
         "ST BOYS": 53807,
         "ST GIRLS": 53807
      }
   },
   "highest_salary": 44.0,
   "lowest_salary": 1.8,
   "salary_mode": 4.0,
   "salary_mean": 5.233125469571751,
   "salary_median": 4.5,
   "total_offers": 1331,
   "compaies_visited": 129,
   "placement_data_year": 2022
}