{
   "closing_ranks_2021": {
      "CSE": {
         "OC BOYS": 18402,
         "OC GIRLS": 18402,
         "BC_A BOYS": 36310,
         "BC_A GIRLS": 43452,
         "BC_B BOYS": 25539,
         "BC_B GIRLS": 30948,
         "BC_C BOYS": 48431,
         "BC_C GIRLS": 48431,
         "BC_D BOYS": 26611,
         "BC_D GIRLS": 27249,
         "BC_E BOYS": 30028,
         "BC_E GIRLS": 38914,
         "SC BOYS": 56702,
         "SC GIRLS": 66954,
         "ST BOYS": 47871,
         "ST GIRLS": 71832
      },
      "CSM": {
         "OC BOYS": 19874,
         "OC GIRLS": 21569,
         "BC_A BOYS": 49113,
         "BC_A GIRLS": 49771,
         "BC_B BOYS": 33891,
         "BC_B GIRLS": 36554,
         "BC_C BOYS": 19874,
         "BC_C GIRLS": 70864,
         "BC_D BOYS": 30253,
         "BC_D GIRLS": 31038,
         "BC_E BOYS": 49624,
         "BC_E GIRLS": 90895,
         "SC BOYS": 75889,
         "SC GIRLS": 93490,
         "ST BOYS": 74619,
         "ST GIRLS": 74619
      },
      "CSD": {
         "OC BOYS": 24244,
         "OC GIRLS": 28992,
         "BC_A BOYS": 55219,
         "BC_A GIRLS": 56630,
         "BC_B BOYS": 35567,
         "BC_B GIRLS": 35567,
         "BC_C BOYS": 24244,
         "BC_C GIRLS": 28992,
         "BC_D BOYS": 36694,
         "BC_D GIRLS": 38746,
         "BC_E BOYS": 69154,
         "BC_E GIRLS": 69154,
         "SC BOYS": 83282,
         "SC GIRLS": 117795,
         "ST BOYS": 75926,
         "ST GIRLS": 75926
      },
      "CSC": {
         "OC BOYS": 27916,
         "OC GIRLS": 30892,
         "BC_A BOYS": 52768,
         "BC_A GIRLS": 52768,
         "BC_B BOYS": 41191,
         "BC_B GIRLS": 42794,
         "BC_C BOYS": 112824,
         "BC_C GIRLS": 112824,
         "BC_D BOYS": 37414,
         "BC_D GIRLS": 40297,
         "BC_E BOYS": 74950,
         "BC_E GIRLS": 74950,
         "SC BOYS": 90819,
         "SC GIRLS": 117778,
         "ST BOYS": 27916,
         "ST GIRLS": 90089
      },
      "INF": {
         "OC BOYS": 29265,
         "OC GIRLS": 29265,
         "BC_A BOYS": 52704,
         "BC_A GIRLS": 52704,
         "BC_B BOYS": 35911,
         "BC_B GIRLS": 43180,
         "BC_C BOYS": 42484,
         "BC_C GIRLS": 45216,
         "BC_D BOYS": 41313,
         "BC_D GIRLS": 44480,
         "BC_E BOYS": 57404,
         "BC_E GIRLS": 95869,
         "SC BOYS": 82158,
         "SC GIRLS": 82158,
         "ST BOYS": 68042,
         "ST GIRLS": 68042
      },
      "CSI": {
         "OC BOYS": 31107,
         "OC GIRLS": 32085,
         "BC_A BOYS": 63963,
         "BC_A GIRLS": 63963,
         "BC_B BOYS": 46591,
         "BC_B GIRLS": 46591,
         "BC_C BOYS": 31107,
         "BC_C GIRLS": 32085,
         "BC_D BOYS": 41011,
         "BC_D GIRLS": 43735,
         "BC_E BOYS": 64057,
         "BC_E GIRLS": 68270,
         "SC BOYS": 105941,
         "SC GIRLS": 108587,
         "ST BOYS": 78818,
         "ST GIRLS": 78818
      },
      "ECE": {
         "OC BOYS": 42950,
         "OC GIRLS": 42950,
         "BC_A BOYS": 76621,
         "BC_A GIRLS": 112324,
         "BC_B BOYS": 60436,
         "BC_B GIRLS": 74770,
         "BC_C BOYS": 56921,
         "BC_C GIRLS": 56921,
         "BC_D BOYS": 56785,
         "BC_D GIRLS": 59994,
         "BC_E BOYS": 106510,
         "BC_E GIRLS": 113448,
         "SC BOYS": 120973,
         "SC GIRLS": 121012,
         "ST BOYS": 87410,
         "ST GIRLS": 87410
      },
      "EEE": {
         "OC BOYS": 50921,
         "OC GIRLS": 84386,
         "BC_A BOYS": 108738,
         "BC_A GIRLS": 112880,
         "BC_B BOYS": 108739,
         "BC_B GIRLS": 108739,
         "BC_C BOYS": 50921,
         "BC_C GIRLS": 84386,
         "BC_D BOYS": 99850,
         "BC_D GIRLS": 99850,
         "BC_E BOYS": 100745,
         "BC_E GIRLS": 100745,
         "SC BOYS": 118445,
         "SC GIRLS": 121396,
         "ST BOYS": 119609,
         "ST GIRLS": 119609
      },
      "MEC": {
         "OC BOYS": 64481,
         "OC GIRLS": 94441,
         "BC_A BOYS": 83245,
         "BC_A GIRLS": 94441,
         "BC_B BOYS": 64481,
         "BC_B GIRLS": 103608,
         "BC_C BOYS": 64481,
         "BC_C GIRLS": 94441,
         "BC_D BOYS": 92839,
         "BC_D GIRLS": 94441,
         "BC_E BOYS": 99530,
         "BC_E GIRLS": 99530,
         "SC BOYS": 64481,
         "SC GIRLS": 94441,
         "ST BOYS": 97175,
         "ST GIRLS": 97175
      },
      "CIV": {
         "OC BOYS": 67743,
         "OC GIRLS": 67743,
         "BC_A BOYS": 105321,
         "BC_A GIRLS": 105321,
         "BC_B BOYS": 98112,
         "BC_B GIRLS": 121250,
         "BC_C BOYS": 67743,
         "BC_C GIRLS": 67743,
         "BC_D BOYS": 97927,
         "BC_D GIRLS": 97927,
         "BC_E BOYS": 67743,
         "BC_E GIRLS": 88753,
         "SC BOYS": 117370,
         "SC GIRLS": 119819,
         "ST BOYS": 117828,
         "ST GIRLS": 117828
      }
   },
   "closing_ranks_2020": {
      "EEE": {
         "OC BOYS": 22388,
         "OC GIRLS": 22388,
         "BC_A BOYS": 82527,
         "BC_A GIRLS": 82527,
         "BC_B BOYS": 72176,
         "BC_B GIRLS": 78317,
         "BC_C BOYS": 22388,
         "BC_C GIRLS": 74750,
         "BC_D BOYS": 57951,
         "BC_D GIRLS": 75910,
         "BC_E BOYS": 32611,
         "BC_E GIRLS": 32611,
         "SC BOYS": 85213,
         "SC GIRLS": 85213,
         "ST BOYS": 62417,
         "ST GIRLS": 67091
      },
      "ECE": {
         "OC BOYS": 30187,
         "OC GIRLS": 30348,
         "BC_A BOYS": 82728,
         "BC_A GIRLS": 83642,
         "BC_B BOYS": 42085,
         "BC_B GIRLS": 46572,
         "BC_C BOYS": 44039,
         "BC_C GIRLS": 44039,
         "BC_D BOYS": 43566,
         "BC_D GIRLS": 48502,
         "BC_E BOYS": 45509,
         "BC_E GIRLS": 82657,
         "SC BOYS": 85652,
         "SC GIRLS": 85785,
         "ST BOYS": 73753,
         "ST GIRLS": 73753
      },
      "CSI": {
         "OC BOYS": 45101,
         "OC GIRLS": 47221,
         "BC_A BOYS": 84372,
         "BC_A GIRLS": 84372,
         "BC_B BOYS": 67085,
         "BC_B GIRLS": 67085,
         "BC_C BOYS": 45101,
         "BC_C GIRLS": 47221,
         "BC_D BOYS": 45101,
         "BC_D GIRLS": 51840,
         "BC_E BOYS": 51246,
         "BC_E GIRLS": 79070,
         "SC BOYS": 70682,
         "SC GIRLS": 70682,
         "ST BOYS": 51056,
         "ST GIRLS": 66528
      },
      "CSE": {
         "OC BOYS": 17824,
         "OC GIRLS": 18725,
         "BC_A BOYS": 40589,
         "BC_A GIRLS": 60943,
         "BC_B BOYS": 33232,
         "BC_B GIRLS": 33264,
         "BC_C BOYS": 17824,
         "BC_C GIRLS": 41303,
         "BC_D BOYS": 28275,
         "BC_D GIRLS": 28275,
         "BC_E BOYS": 51701,
         "BC_E GIRLS": 85216,
         "SC BOYS": 65585,
         "SC GIRLS": 74432,
         "ST BOYS": 53907,
         "ST GIRLS": 82488
      },
      "INF": {
         "OC BOYS": 23534,
         "OC GIRLS": 25017,
         "BC_A BOYS": 68735,
         "BC_A GIRLS": 83304,
         "BC_B BOYS": 37273,
         "BC_B GIRLS": 41799,
         "BC_C BOYS": 23534,
         "BC_C GIRLS": 25017,
         "BC_D BOYS": 35287,
         "BC_D GIRLS": 36704,
         "BC_E BOYS": 52370,
         "BC_E GIRLS": 59211,
         "SC BOYS": 74524,
         "SC GIRLS": 76258,
         "ST BOYS": 46288,
         "ST GIRLS": 81007
      },
      "CSD": {
         "OC BOYS": 36724,
         "OC GIRLS": 36724,
         "BC_A BOYS": 60688,
         "BC_A GIRLS": 60688,
         "BC_B BOYS": 65023,
         "BC_B GIRLS": 66914,
         "BC_C BOYS": 36724,
         "BC_C GIRLS": 36724,
         "BC_D BOYS": 44350,
         "BC_D GIRLS": 45026,
         "BC_E BOYS": 59588,
         "BC_E GIRLS": 59588,
         "SC BOYS": 79188,
         "SC GIRLS": 79188,
         "ST BOYS": 74538,
         "ST GIRLS": 74538
      },
      "CSC": {
         "OC BOYS": 37617,
         "OC GIRLS": 42262,
         "BC_A BOYS": 56291,
         "BC_A GIRLS": 56291,
         "BC_B BOYS": 56798,
         "BC_B GIRLS": 66090,
         "BC_C BOYS": 46399,
         "BC_C GIRLS": 46399,
         "BC_D BOYS": 46887,
         "BC_D GIRLS": 52446,
         "BC_E BOYS": 60987,
         "BC_E GIRLS": 66136,
         "SC BOYS": 85281,
         "SC GIRLS": 85281,
         "ST BOYS": 69267,
         "ST GIRLS": 72312
      },
      "MEC": {
         "OC BOYS": 51935,
         "OC GIRLS": 51935,
         "BC_A BOYS": 61157,
         "BC_A GIRLS": 63686,
         "BC_B BOYS": 77350,
         "BC_B GIRLS": 77350,
         "BC_C BOYS": 51935,
         "BC_C GIRLS": 51935,
         "BC_D BOYS": 73949,
         "BC_D GIRLS": 78247,
         "BC_E BOYS": 70568,
         "BC_E GIRLS": 70568,
         "SC BOYS": 85552,
         "SC GIRLS": 85552,
         "ST BOYS": 80408,
         "ST GIRLS": 81366
      },
      "CIV": {
         "OC BOYS": 38954,
         "OC GIRLS": 44472,
         "BC_A BOYS": 81803,
         "BC_A GIRLS": 81803,
         "BC_B BOYS": 56490,
         "BC_B GIRLS": 78400,
         "BC_C BOYS": 51419,
         "BC_C GIRLS": 51419,
         "BC_D BOYS": 72060,
         "BC_D GIRLS": 72060,
         "BC_E BOYS": 84293,
         "BC_E GIRLS": 84293,
         "SC BOYS": 80169,
         "SC GIRLS": 83509,
         "ST BOYS": 65822,
         "ST GIRLS": 69396
      },
      "CSM": {
         "OC BOYS": 22750,
         "OC GIRLS": 22750,
         "BC_A BOYS": 55338,
         "BC_A GIRLS": 65201,
         "BC_B BOYS": 31922,
         "BC_B GIRLS": 57142,
         "BC_C BOYS": 42495,
         "BC_C GIRLS": 42495,
         "BC_D BOYS": 41277,
         "BC_D GIRLS": 41388,
         "BC_E BOYS": 84306,
         "BC_E GIRLS": 84306,
         "SC BOYS": 78242,
         "SC GIRLS": 78242,
         "ST BOYS": 67491,
         "ST GIRLS": 77506
      }
   },
   "closing_ranks_2019": {
      "INF": {
         "OC BOYS": 28373,
         "OC GIRLS": 30242,
         "BC_A BOYS": 71123,
         "BC_A GIRLS": 74855,
         "BC_B BOYS": 40757,
         "BC_B GIRLS": 40757,
         "BC_C BOYS": 45836,
         "BC_C GIRLS": 45836,
         "BC_D BOYS": 45598,
         "BC_D GIRLS": 45598,
         "BC_E BOYS": 28373,
         "BC_E GIRLS": 30242,
         "SC BOYS": 81771,
         "SC GIRLS": 81771,
         "ST BOYS": 31225,
         "ST GIRLS": 31225
      },
      "ECE": {
         "OC BOYS": 33313,
         "OC GIRLS": 33373,
         "BC_A BOYS": 85962,
         "BC_A GIRLS": 85962,
         "BC_B BOYS": 51823,
         "BC_B GIRLS": 51823,
         "BC_C BOYS": 47625,
         "BC_C GIRLS": 47625,
         "BC_D BOYS": 47590,
         "BC_D GIRLS": 47590,
         "BC_E BOYS": 53161,
         "BC_E GIRLS": 54376,
         "SC BOYS": 86165,
         "SC GIRLS": 86165,
         "ST BOYS": 36898,
         "ST GIRLS": 71156
      },
      "CSE": {
         "OC BOYS": 22100,
         "OC GIRLS": 22100,
         "BC_A BOYS": 47804,
         "BC_A GIRLS": 74741,
         "BC_B BOYS": 34198,
         "BC_B GIRLS": 34198,
         "BC_C BOYS": 72850,
         "BC_C GIRLS": 72850,
         "BC_D BOYS": 33062,
         "BC_D GIRLS": 33468,
         "BC_E BOYS": 64333,
         "BC_E GIRLS": 64333,
         "SC BOYS": 81680,
         "SC GIRLS": 81680,
         "ST BOYS": 76554,
         "ST GIRLS": 83998
      },
      "MEC": {
         "OC BOYS": 69367,
         "OC GIRLS": 69367,
         "BC_A BOYS": 84627,
         "BC_A GIRLS": 87656,
         "BC_B BOYS": 85140,
         "BC_B GIRLS": 85140,
         "BC_C BOYS": 69367,
         "BC_C GIRLS": 69367,
         "BC_D BOYS": 75880,
         "BC_D GIRLS": 75880,
         "BC_E BOYS": 69367,
         "BC_E GIRLS": 69367,
         "SC BOYS": 89494,
         "SC GIRLS": 89494,
         "ST BOYS": 69367,
         "ST GIRLS": 69367
      },
      "CIV": {
         "OC BOYS": 48723,
         "OC GIRLS": 60024,
         "BC_A BOYS": 90008,
         "BC_A GIRLS": 90008,
         "BC_B BOYS": 83407,
         "BC_B GIRLS": 83407,
         "BC_C BOYS": 48723,
         "BC_C GIRLS": 60024,
         "BC_D BOYS": 62762,
         "BC_D GIRLS": 77726,
         "BC_E BOYS": 79090,
         "BC_E GIRLS": 83453,
         "SC BOYS": 91114,
         "SC GIRLS": 91114,
         "ST BOYS": 84056,
         "ST GIRLS": 84723
      },
      "EEE": {
         "OC BOYS": 39254,
         "OC GIRLS": 39949,
         "BC_A BOYS": 67241,
         "BC_A GIRLS": 69760,
         "BC_B BOYS": 69613,
         "BC_B GIRLS": 69613,
         "BC_C BOYS": 55794,
         "BC_C GIRLS": 55794,
         "BC_D BOYS": 59580,
         "BC_D GIRLS": 71143,
         "BC_E BOYS": 83721,
         "BC_E GIRLS": 83721,
         "SC BOYS": 68354,
         "SC GIRLS": 68354,
         "ST BOYS": 75363,
         "ST GIRLS": 75363
      }
   },
   "highest_salary": 18.0,
   "lowest_salary": 1.8,
   "salary_mode": 3.5,
   "salary_mean": 3.9170454545454545,
   "salary_median": 3.5,
   "total_offers": 748,
   "compaies_visited": 64,
   "placement_data_year": 2022
}